termcolor_dg.py
termcolor_dg-1.0.2.dist-info/LICENSE
termcolor_dg-1.0.2.dist-info/METADATA
termcolor_dg-1.0.2.dist-info/WHEEL
termcolor_dg-1.0.2.dist-info/entry_points.txt
termcolor_dg-1.0.2.dist-info/top_level.txt
termcolor_dg-1.0.2.dist-info/RECORD
