Metadata-Version: 2.1
Name: termcolor_dg
Version: 1.0.2
Summary: ANSI Color formatting for terminal output and log coloring
Home-page: https://github.com/gunchev/termcolor_dg/
Author: Konstantin Lepa
Author-email: konstantin.lepa@gmail.com
Maintainer: Doncho N. Gunchev
Maintainer-email: dgunchev@gmail.com
License: MIT
Project-URL: Source, https://github.com/gunchev/termcolor_dg/
Project-URL: Bug Tracker, https://github.com/gunchev/termcolor_dg/issues/
Project-URL: Documentation, https://github.com/gunchev/termcolor_dg/blob/master/README.md
Platform: any
Classifier: Development Status :: 5 - Production/Stable
Classifier: License :: OSI Approved :: MIT License
Classifier: Operating System :: OS Independent
Classifier: Programming Language :: Python
Classifier: Programming Language :: Python :: 2
Classifier: Programming Language :: Python :: 3
Classifier: Environment :: Console
Classifier: Topic :: Terminals
Classifier: Topic :: Software Development
Classifier: Intended Audience :: Developers
Requires-Python: >=2.7
License-File: LICENSE
